DadilipTrainer/DadilipTrainer.py
DadilipTrainer/__init__.py
DadilipTrainer-0.1.0.dist-info/LICENSE
DadilipTrainer-0.1.0.dist-info/METADATA
DadilipTrainer-0.1.0.dist-info/WHEEL
DadilipTrainer-0.1.0.dist-info/top_level.txt
DadilipTrainer-0.1.0.dist-info/RECORD
